[
  {
    "title": "TV Rant Character (Transparent)",
    "type": "png",
    "tags": [
      "satire",
      "transparent",
      "character",
      "tv",
      "mic"
    ],
    "date": "2026-01-31",
    "download": "/assets/members/satire/tv-rant-transparent.png"
  },
  {
    "title": "Moe News Not Even Worth Sh*t (Sticker)",
    "type": "png",
    "tags": [
      "satire",
      "transparent",
      "sticker",
      "moe",
      "news"
    ],
    "date": "2026-01-31",
    "download": "/assets/members/satire/moe-news-not-worth-sticker.png"
  },
  {
    "title": "Satire Pack: Starter Bundle",
    "type": "zip",
    "tags": [
      "satire",
      "pack",
      "zip"
    ],
    "date": "2026-01-31",
    "download": "/assets/members/satire/satire-pack-starter.zip"
  },
  {
    "title": "Thumbnail Template: Satire Frame",
    "type": "template",
    "tags": [
      "template",
      "thumbnail",
      "satire"
    ],
    "date": "2026-01-31",
    "download": "/assets/members/satire/thumbnail-template.png"
  }
]